{
  "version": "7",
  "dialect": "postgresql",
  "entries": [
    {
      "idx": 0,
      "version": "7",
      "when": 1775920628004,
      "tag": "0000_nasty_madame_hydra",
      "breakpoints": true
    },
    {
      "idx": 1,
      "version": "7",
      "when": 1775952576457,
      "tag": "0001_round_the_call",
      "breakpoints": true
    },
    {
      "idx": 2,
      "version": "7",
      "when": 1775952699105,
      "tag": "0002_overrated_alex_power",
      "breakpoints": true
    },
    {
      "idx": 3,
      "version": "7",
      "when": 1775952981607,
      "tag": "0003_whole_vector",
      "breakpoints": true
    },
    {
      "idx": 4,
      "version": "7",
      "when": 1775953895737,
      "tag": "0004_majestic_ultimatum",
      "breakpoints": true
    },
    {
      "idx": 5,
      "version": "7",
      "when": 1775956207616,
      "tag": "0005_bent_domino",
      "breakpoints": true
    },
    {
      "idx": 6,
      "version": "7",
      "when": 1776072355525,
      "tag": "0006_abandoned_robbie_robertson",
      "breakpoints": true
    },
    {
      "idx": 7,
      "version": "7",
      "when": 1776220800000,
      "tag": "0007_task_chat_run",
      "breakpoints": true
    },
    {
      "idx": 8,
      "version": "7",
      "when": 1776153549897,
      "tag": "0008_sharp_dust",
      "breakpoints": true
    }
  ]
}
